[{"1.Lokasi":"Jatinegara, Jakarta","1.Nama Dokter":"Dr. drg. Dewi Anggraini Margono Rompas, Sp.KG(K)","1.Spesialis":"Dokter Gigi","1.Tarif":"Mulai Dari Rp 350.000","1.Tempat Praktik":"Rumah Sakit Premier Jatinegara","10.Lokasi":"Jatinegara, Jakarta","10.Nama Dokter":"drg. Maswati, Sp.KG","10.Spesialis":"Dokter Gigi","10.Tarif":"Mulai Dari Rp 300.000","10.Tempat Praktik":"Rumah Sakit Premier Jatinegara","11.Lokasi":"Jatinegara, Jakarta","11.Nama Dokter":"drg. Lilies Dwi Sulistyani, Sp.BM","11.Spesialis":"Dokter Gigi","11.Tarif":"Mulai Dari Rp 300.000","11.Tempat Praktik":"Rumah Sakit Premier Jatinegara","12.Lokasi":"Jatinegara, Jakarta","12.Nama Dokter":"drg. Sally Irawati S, Sp.KG","12.Spesialis":"Dokter Gigi","12.Tarif":"Mulai Dari Rp 250.000","12.Tempat Praktik":"Rumah Sakit Premier Jatinegara","13.Lokasi":"Pondok Aren, Tangerang","13.Nama Dokter":"drg. Dewi Haryanti Pramono, Sp.Pros","13.Spesialis":"Dokter Gigi","13.Tarif":"Mulai Dari Rp 300.000","13.Tempat Praktik":"Rumah Sakit Premier Bintaro","14.Lokasi":"Pondok Aren, Tangerang","14.Nama Dokter":"drg. Gunawan Atmadja, Sp.KG, MDSc","14.Spesialis":"Dokter Gigi","14.Tarif":"Mulai Dari Rp 300.000","14.Tempat Praktik":"Rumah Sakit Premier Bintaro","15.Lokasi":"Pondok Aren, Tangerang","15.Nama Dokter":"drg. Henny Mounadevi Adrianne, Sp.KG","15.Spesialis":"Dokter Gigi","15.Tarif":"Mulai Dari Rp 300.000","15.Tempat Praktik":"Rumah Sakit Premier Bintaro","16.Lokasi":"Pondok Aren, Tangerang","16.Nama Dokter":"drg. Hendrarlin Soenawan, Sp.KGA(K)","16.Spesialis":"Dokter Gigi","16.Tarif":"Mulai Dari Rp 300.000","16.Tempat Praktik":"Rumah Sakit Premier Bintaro","17.Lokasi":"Pondok Aren, Tangerang","17.Nama Dokter":"drg. Agustine Irene Sukardi, Sp.Perio","17.Spesialis":"Dokter Gigi","17.Tarif":"Mulai Dari Rp 300.000","17.Tempat Praktik":"Rumah Sakit Premier Bintaro","18.Lokasi":"Pondok Aren, Tangerang","18.Nama Dokter":"drg. Laksmi Wijayanti Baskoro, Sp.KG","18.Spesialis":"Dokter Gigi","18.Tarif":"Mulai Dari Rp 300.000","18.Tempat Praktik":"Rumah Sakit Premier Bintaro","19.Lokasi":"Pondok Aren, Tangerang","19.Nama Dokter":"drg. Adhyana Satya Novanto","19.Spesialis":"Dokter Gigi","19.Tarif":"Mulai Dari Rp 300.000","19.Tempat Praktik":"Rumah Sakit Premier Bintaro","2.Lokasi":"Pondok Aren, Tangerang","2.Nama Dokter":"drg. Gatot Sutrisno, Sp.KG (K)","2.Spesialis":"Dokter Gigi","2.Tarif":"Mulai Dari Rp 300.000","2.Tempat Praktik":"Rumah Sakit Premier Bintaro","20.Lokasi":"Pondok Aren, Tangerang","20.Nama Dokter":"drg. Anak Agung Ayu Satyawati, Sp.Ort","20.Spesialis":"Dokter Gigi","20.Tarif":"Mulai Dari Rp 300.000","20.Tempat Praktik":"Rumah Sakit Premier Bintaro","21.Lokasi":"Pondok Aren, Tangerang","21.Nama Dokter":"drg. Sjahril Noerdin, Sp.KGA","21.Spesialis":"Dokter Gigi","21.Tarif":"Mulai Dari Rp 300.000","21.Tempat Praktik":"Rumah Sakit Premier Bintaro","22.Lokasi":"Pondok Aren, Tangerang","22.Nama Dokter":"drg. Sonya Susanti Kemalasari","22.Spesialis":"Dokter Gigi","22.Tarif":"Mulai Dari Rp 300.000","22.Tempat Praktik":"Rumah Sakit Premier Bintaro","23.Lokasi":"Pondok Aren, Tangerang","23.Nama Dokter":"drg. Rahmita Nuraini, Sp.KGA","23.Spesialis":"Dokter Gigi","23.Tarif":"Mulai Dari Rp 300.000","23.Tempat Praktik":"Rumah Sakit Premier Bintaro","24.Lokasi":"Pondok Aren, Tangerang","24.Nama Dokter":"drg. Shalina Ricardo","24.Spesialis":"Dokter Gigi","24.Tarif":"Mulai Dari Rp 300.000","24.Tempat Praktik":"Rumah Sakit Premier Bintaro","25.Lokasi":"Sukolilo, Surabaya","25.Nama Dokter":"drg. Lina Purnama, Sp.Ort","25.Spesialis":"Dokter Gigi","25.Tarif":"Mulai Dari Rp 250.000","25.Tempat Praktik":"Rumah Sakit Premier Surabaya","26.Lokasi":"Kelapa Dua, Tangerang","26.Nama Dokter":"drg. Didiek Andries, Sp.KG","26.Spesialis":"Dokter Gigi","26.Tarif":"Mulai Dari Rp 300.000","26.Tempat Praktik":"Siloam Hospitals Lippo Village","27.Lokasi":"Cilandak, Jakarta","27.Nama Dokter":"drg. Kurnia Natalia Kusumo, Sp.BM","27.Spesialis":"Dokter Gigi","27.Tarif":"Mulai Dari Rp 300.000","27.Tempat Praktik":"Siloam Hospitals TB Simatupang","28.Lokasi":"Cilandak, Jakarta","28.Nama Dokter":"drg. Irenia Tamany","28.Spesialis":"Dokter Gigi","28.Tarif":"Mulai Dari Rp 300.000","28.Tempat Praktik":"Siloam Hospitals TB Simatupang","29.Lokasi":"Cilandak, Jakarta","29.Nama Dokter":"drg. Yunita Tri Anandi, Sp.KGA","29.Spesialis":"Dokter Gigi","29.Tarif":"Mulai Dari Rp 300.000","29.Tempat Praktik":"Siloam Hospitals TB Simatupang","3.Lokasi":"Sukolilo, Surabaya","3.Nama Dokter":"drg. Atje Swandhani Soenata","3.Spesialis":"Dokter Gigi","3.Tarif":"Mulai Dari Rp 200.000","3.Tempat Praktik":"Rumah Sakit Premier Surabaya","30.Lokasi":"Cilandak, Jakarta","30.Nama Dokter":"drg. Annisa Kheria, Sp.KG","30.Spesialis":"Dokter Gigi","30.Tarif":"Mulai Dari Rp 300.000","30.Tempat Praktik":"Siloam Hospitals TB Simatupang","31.Lokasi":"Cilandak, Jakarta","31.Nama Dokter":"drg. Fetriana, Sp.KG","31.Spesialis":"Dokter Gigi","31.Tarif":"Mulai Dari Rp 300.000","31.Tempat Praktik":"Siloam Hospitals TB Simatupang","32.Lokasi":"Cilandak, Jakarta","32.Nama Dokter":"drg. Hendro Priyo Dwi Utomo","32.Spesialis":"Dokter Gigi","32.Tarif":"Mulai Dari Rp 300.000","32.Tempat Praktik":"Siloam Hospitals TB Simatupang","33.Lokasi":"Cilandak, Jakarta","33.Nama Dokter":"drg. Minawati Hartanto","33.Spesialis":"Dokter Gigi","33.Tarif":"Mulai Dari Rp 300.000","33.Tempat Praktik":"Siloam Hospitals TB Simatupang","34.Lokasi":"Cilandak, Jakarta","34.Nama Dokter":"drg. Reiny Agustina","34.Spesialis":"Dokter Gigi","34.Tarif":"Mulai Dari Rp 300.000","34.Tempat Praktik":"Siloam Hospitals TB Simatupang","35.Lokasi":"Cilandak, Jakarta","35.Nama Dokter":"drg. Hara Pardamean Hutabarat","35.Spesialis":"Dokter Gigi","35.Tarif":"Mulai Dari Rp 300.000","35.Tempat Praktik":"Siloam Hospitals TB Simatupang","36.Lokasi":"Jatinegara, Jakarta","36.Nama Dokter":"drg. Kismanto, Sp.BM","36.Spesialis":"Dokter Gigi","36.Tarif":"Mulai Dari Rp 250.000","36.Tempat Praktik":"Rumah Sakit Premier Jatinegara","37.Lokasi":"Jatinegara, Jakarta","37.Nama Dokter":"drg. Elisabeth Leksonowati","37.Spesialis":"Dokter Gigi","37.Tarif":"Mulai Dari Rp 250.000","37.Tempat Praktik":"Rumah Sakit Premier Jatinegara","38.Lokasi":"Jatinegara, Jakarta","38.Nama Dokter":"drg. Margaretha Grace Lumempouw, Sp.Pros","38.Spesialis":"Dokter Gigi","38.Tarif":"Mulai Dari Rp 300.000","38.Tempat Praktik":"Rumah Sakit Premier Jatinegara","39.Lokasi":"Jatinegara, Jakarta","39.Nama Dokter":"drg. Debora Remalya, Sp.KG","39.Spesialis":"Dokter Gigi","39.Tarif":"Mulai Dari Rp 250.000","39.Tempat Praktik":"Rumah Sakit Premier Jatinegara","4.Lokasi":"Kelapa Dua, Tangerang","4.Nama Dokter":"drg. Sri Rahayu, Sp.Perio","4.Spesialis":"Dokter Gigi","4.Tarif":"Mulai Dari Rp 300.000","4.Tempat Praktik":"Siloam Hospitals Lippo Village","40.Lokasi":"Pondok Aren, Tangerang","40.Nama Dokter":"drg. Dimas Mahardhika, Sp.BM","40.Spesialis":"Dokter Gigi","40.Tarif":"Mulai Dari Rp 300.000","40.Tempat Praktik":"Rumah Sakit Premier Bintaro","41.Lokasi":"Pondok Aren, Tangerang","41.Nama Dokter":"drg. Lilies B Nugroho, Sp.BM","41.Spesialis":"Dokter Gigi","41.Tarif":"Mulai Dari Rp 300.000","41.Tempat Praktik":"Rumah Sakit Premier Bintaro","42.Lokasi":"Gubeng, Surabaya","42.Nama Dokter":"Dr. drg. Tamara Yuanita, MS, Sp.KG","42.Spesialis":"Dokter Gigi","42.Tarif":"Mulai Dari Rp 400.000","42.Tempat Praktik":"Siloam Hospitals Surabaya","43.Lokasi":"Gubeng, Surabaya","43.Nama Dokter":"drg. Galih Sampoerno, M.Kes, Sp.KG","43.Spesialis":"Dokter Gigi","43.Tarif":"Mulai Dari Rp 350.000","43.Tempat Praktik":"Siloam Hospitals Surabaya","44.Lokasi":"Gubeng, Surabaya","44.Nama Dokter":"drg. Muji Lestari, Sp.KG","44.Spesialis":"Dokter Gigi","44.Tarif":"Mulai Dari Rp 250.000","44.Tempat Praktik":"Siloam Hospitals Surabaya","45.Lokasi":"Gubeng, Surabaya","45.Nama Dokter":"drg. Ninik Indrawati","45.Spesialis":"Dokter Gigi","45.Tarif":"Mulai Dari Rp 250.000","45.Tempat Praktik":"Siloam Hospitals Surabaya","46.Lokasi":"Sukolilo, Surabaya","46.Nama Dokter":"drg. Roosanti Nurwinda Purisari, Sp.KGA","46.Spesialis":"Dokter Gigi","46.Tarif":"Mulai Dari Rp 200.000","46.Tempat Praktik":"Rumah Sakit Bedah Surabaya","47.Lokasi":"Bali","47.Nama Dokter":"drg. Putu Ari Listya Nurina","47.Spesialis":"Dokter Gigi","47.Tarif":"Mulai Dari Rp 380.000","47.Tempat Praktik":"BIMC Siloam Hospital Nusa Dua","48.Lokasi":"Bali","48.Nama Dokter":"drg. Harry Iskandar, Sp.Pros","48.Spesialis":"Dokter Gigi","48.Tarif":"Mulai Dari Rp 380.000","48.Tempat Praktik":"BIMC Siloam Hospital Nusa Dua","49.Lokasi":"Setiabudi, Jakarta","49.Nama Dokter":"drg. Bernadi C. Into, Sp.Pros","49.Spesialis":"Dokter Gigi","49.Tarif":"Mulai Dari Rp 600.000","49.Tempat Praktik":"MRCCC Siloam Hospitals Semanggi","5.Lokasi":"Cilandak, Jakarta","5.Nama Dokter":"dr. Cahyaningrum Sekar Ardiasti Sp.KGA","5.Spesialis":"Dokter Gigi","5.Tarif":"Mulai Dari Rp 300.000","5.Tempat Praktik":"Siloam Hospitals TB Simatupang","50.Lokasi":"Setiabudi, Jakarta","50.Nama Dokter":"drg. Devina Setiadi, Sp.KG","50.Spesialis":"Dokter Gigi","50.Tarif":"Mulai Dari Rp 250.000","50.Tempat Praktik":"MRCCC Siloam Hospitals Semanggi","51.Lokasi":"Jatinegara, Jakarta","51.Nama Dokter":"drg. Iva Permatasari, Sp.KGA","51.Spesialis":"Dokter Gigi","51.Tarif":"Mulai Dari Rp 300.000","51.Tempat Praktik":"Rumah Sakit Premier Jatinegara","52.Lokasi":"Jatinegara, Jakarta","52.Nama Dokter":"drg. Trisnawati Riana Indari, Sp.KG","52.Spesialis":"Dokter Gigi","52.Tarif":"Mulai Dari Rp 250.000","52.Tempat Praktik":"Rumah Sakit Premier Jatinegara","53.Lokasi":"Pondok Aren, Tangerang","53.Nama Dokter":"Dr. drg. Maria Purbiati Indratoto, Sp.Ort(K)","53.Spesialis":"Dokter Gigi","53.Tarif":"Mulai Dari Rp 300.000","53.Tempat Praktik":"Rumah Sakit Premier Bintaro","54.Lokasi":"Sukolilo, Surabaya","54.Nama Dokter":"drg. Ari Mardhika Indriyasari","54.Spesialis":"Dokter Gigi","54.Tarif":"Mulai Dari Rp 200.000","54.Tempat Praktik":"Rumah Sakit Bedah Surabaya","55.Lokasi":"Sukolilo, Surabaya","55.Nama Dokter":"drg. Yoifah Rizka Wedarti, Sp.Perio","55.Spesialis":"Dokter Gigi","55.Tarif":"Mulai Dari Rp 200.000","55.Tempat Praktik":"Rumah Sakit Bedah Surabaya","56.Lokasi":"Sukolilo, Surabaya","56.Nama Dokter":"drg. Juli Larasati, Sp.KG","56.Spesialis":"Dokter Gigi","56.Tarif":"Mulai Dari Rp 200.000","56.Tempat Praktik":"Rumah Sakit Bedah Surabaya","57.Lokasi":"Sukolilo, Surabaya","57.Nama Dokter":"drg. Nurul Maulidah, Sp.BM","57.Spesialis":"Dokter Gigi","57.Tarif":"Mulai Dari Rp 200.000","57.Tempat Praktik":"Rumah Sakit Bedah Surabaya","58.Lokasi":"Sukolilo, Surabaya","58.Nama Dokter":"drg. Enny Wilianti","58.Spesialis":"Dokter Gigi","58.Tarif":"Mulai Dari Rp 250.000","58.Tempat Praktik":"Rumah Sakit Premier Surabaya","59.Lokasi":"Pancoran, Jakarta","59.Nama Dokter":"Prof. drg. Heriandi Sutadi, Sp.KGA (K), Ph.D","59.Spesialis":"Dokter Gigi","59.Tarif":"Mulai Dari Rp 425.000","59.Tempat Praktik":"Siloam Hospitals Asri Mampang","6.Lokasi":"Cikarang","6.Nama Dokter":"drg. Christiana Dewi Anggriani, Sp.KG","6.Spesialis":"Dokter Gigi","6.Tarif":"Mulai Dari Rp 200.000","6.Tempat Praktik":"Siloam Hospitals Lippo Cikarang","60.Lokasi":"Cikarang","60.Nama Dokter":"drg. Danesa Tanzil","60.Spesialis":"Dokter Gigi","60.Tarif":"Mulai Dari Rp 150.000","60.Tempat Praktik":"Siloam Hospitals Lippo Cikarang","61.Lokasi":"Cikarang","61.Nama Dokter":"drg. Devi Ekawati","61.Spesialis":"Dokter Gigi","61.Tarif":"Mulai Dari Rp 150.000","61.Tempat Praktik":"Siloam Hospitals Lippo Cikarang","62.Lokasi":"Cikarang","62.Nama Dokter":"drg. Dona Angelica Eridani, Sp.Pros","62.Spesialis":"Dokter Gigi","62.Tarif":"Mulai Dari Rp 150.000","62.Tempat Praktik":"Siloam Hospitals Lippo Cikarang","63.Lokasi":"Cikarang","63.Nama Dokter":"drg. Fransiscus Djaja Gunawan, M.Kes","63.Spesialis":"Dokter Gigi","63.Tarif":"Mulai Dari Rp 200.000","63.Tempat Praktik":"Siloam Hospitals Lippo Cikarang","64.Lokasi":"Cikarang","64.Nama Dokter":"drg. Hendratna Setyabudi","64.Spesialis":"Dokter Gigi","64.Tarif":"Mulai Dari Rp 150.000","64.Tempat Praktik":"Siloam Hospitals Lippo Cikarang","65.Lokasi":"Semarang","65.Nama Dokter":"drg. Yosef Santosa Widjaja","65.Spesialis":"Dokter Gigi","65.Tarif":"Mulai Dari Rp 200.000","65.Tempat Praktik":"Rumah Sakit Telogorejo","66.Lokasi":"Semarang","66.Nama Dokter":"drg. Imelda Susanti Hartono","66.Spesialis":"Dokter Gigi","66.Tarif":"Mulai Dari Rp 200.000","66.Tempat Praktik":"Rumah Sakit Telogorejo","67.Lokasi":"Semarang","67.Nama Dokter":"drg. Bambang Priyatno, Sp.BM","67.Spesialis":"Dokter Gigi","67.Tarif":"Mulai Dari Rp 250.000","67.Tempat Praktik":"Rumah Sakit Telogorejo","68.Lokasi":"Semarang","68.Nama Dokter":"drg. Oentoro Ermes Harmono, Sp. BM","68.Spesialis":"Dokter Gigi","68.Tarif":"Mulai Dari Rp 250.000","68.Tempat Praktik":"Rumah Sakit Telogorejo","69.Lokasi":"Semarang","69.Nama Dokter":"drg. Agustinus Purnawan Handoko, Sp.BM","69.Spesialis":"Dokter Gigi","69.Tarif":"Mulai Dari Rp 250.000","69.Tempat Praktik":"Rumah Sakit Telogorejo","7.Lokasi":"Medan","7.Nama Dokter":"drg. Denny Rinto Alam","7.Spesialis":"Dokter Gigi","7.Tarif":"Mulai Dari Rp 150.000","7.Tempat Praktik":"Rumah Sakit Siloam Dhirga Surya","70.Lokasi":"Kelapa Dua, Tangerang","70.Nama Dokter":"drg. Kris Toetik, Sp.Ort","70.Spesialis":"Dokter Gigi","70.Tarif":"Mulai Dari Rp 300.000","70.Tempat Praktik":"Siloam Hospitals Lippo Village","71.Lokasi":"Kelapa Dua, Tangerang","71.Nama Dokter":"drg. Andri Hardianto, Sp.BM","71.Spesialis":"Dokter Gigi","71.Tarif":"Mulai Dari Rp 300.000","71.Tempat Praktik":"Siloam Hospitals Lippo Village","72.Lokasi":"Kelapa Dua, Tangerang","72.Nama Dokter":"drg. Buddiwati Punta, Sp.KG","72.Spesialis":"Dokter Gigi","72.Tarif":"Mulai Dari Rp 300.000","72.Tempat Praktik":"Siloam Hospitals Lippo Village","73.Lokasi":"Kelapa Dua, Tangerang","73.Nama Dokter":"drg. Inawati Muljadi, Sp.KG","73.Spesialis":"Dokter Gigi","73.Tarif":"Mulai Dari Rp 300.000","73.Tempat Praktik":"Siloam Hospitals Lippo Village","74.Lokasi":"Cilandak, Jakarta","74.Nama Dokter":"dr. Widyanti Pratiwi, Sp.KGA","74.Spesialis":"Dokter Gigi","74.Tarif":"Mulai Dari Rp 300.000","74.Tempat Praktik":"Siloam Hospitals TB Simatupang","75.Lokasi":"Cilandak, Jakarta","75.Nama Dokter":"drg. Hayana Miguna, Sp.BM","75.Spesialis":"Dokter Gigi","75.Tarif":"Mulai Dari Rp 300.000","75.Tempat Praktik":"Siloam Hospitals TB Simatupang","76.Lokasi":"Bogor Tengah, Bogor","76.Nama Dokter":"drg. Jessica Wahyuni","76.Spesialis":"Dokter Gigi","76.Tarif":"Mulai Dari Rp 200.000","76.Tempat Praktik":"Siloam Hospitals Bogor","77.Lokasi":"Bogor Tengah, Bogor","77.Nama Dokter":"drg. Evy Indriani Vyati, Sp.B","77.Spesialis":"Dokter Gigi","77.Tarif":"Mulai Dari Rp 200.000","77.Tempat Praktik":"Siloam Hospitals Bogor","78.Lokasi":"Kupang","78.Nama Dokter":"drg. Alice Ritliany","78.Spesialis":"Dokter Gigi","78.Tarif":"Mulai Dari Rp 130.000","78.Tempat Praktik":"Siloam Hospitals Kupang","79.Lokasi":"Kupang","79.Nama Dokter":"drg. Lily Liana","79.Spesialis":"Dokter Gigi","79.Tarif":"Mulai Dari Rp 130.000","79.Tempat Praktik":"Siloam Hospitals Kupang","8.Lokasi":"Balikpapan","8.Nama Dokter":"drg. Patar Jackson","8.Spesialis":"Dokter Gigi","8.Tarif":"Mulai Dari Rp 200.000","8.Tempat Praktik":"Siloam Hospitals Balikpapan","80.Lokasi":"Balikpapan","80.Nama Dokter":"drg. Felicia Melati Sp.KGA","80.Spesialis":"Dokter Gigi","80.Tarif":"Mulai Dari Rp 200.000","80.Tempat Praktik":"Siloam Hospitals Balikpapan","81.Lokasi":"Balikpapan","81.Nama Dokter":"drg. Yulia Fitri Olla","81.Spesialis":"Dokter Gigi","81.Tarif":"Mulai Dari Rp 200.000","81.Tempat Praktik":"Siloam Hospitals Balikpapan","82.Lokasi":"Balikpapan","82.Nama Dokter":"drg. Daniel T.H Hutabarat, Sp.BM","82.Spesialis":"Dokter Gigi","82.Tarif":"Mulai Dari Rp 200.000","82.Tempat Praktik":"Siloam Hospitals Balikpapan","83.Lokasi":"Balikpapan","83.Nama Dokter":"drg. Eviwati Sitanggang, Sp.BM","83.Spesialis":"Dokter Gigi","83.Tarif":"Mulai Dari Rp 200.000","83.Tempat Praktik":"Siloam Hospitals Balikpapan","84.Lokasi":"Labuan Bajo","84.Nama Dokter":"drg. Suryani Chen","84.Spesialis":"Dokter Gigi","84.Tarif":"","84.Tempat Praktik":"Siloam Hospitals Labuan Bajo","9.Lokasi":"Kebayoran Baru, Jakarta","9.Nama Dokter":"drg. Asdi Zen","9.Spesialis":"Dokter Gigi","9.Tarif":"Mulai Dari Rp 250.000","9.Tempat Praktik":"SamMarie Wijaya"}]